reddit/__init__.py
reddit/constants.py
reddit/scraper.py
reddit/util.py
reddit_api_client-0.0.0.dist-info/LICENSE
reddit_api_client-0.0.0.dist-info/METADATA
reddit_api_client-0.0.0.dist-info/WHEEL
reddit_api_client-0.0.0.dist-info/top_level.txt
reddit_api_client-0.0.0.dist-info/RECORD
