Metadata-Version: 2.1
Name: reddit-api-client
Version: 0.0.0
Summary: Reddit API
Home-page: https://github.com/trevorhobenshield/reddit-api-client
Author: Trevor Hobenshield
Author-email: trevorhobenshield@gmail.com
Keywords: reddit api client async search automation bot scrape
Requires-Python: >=3.10.10
License-File: LICENSE
Requires-Dist: aiofiles
Requires-Dist: websockets
Requires-Dist: nest-asyncio
Requires-Dist: httpx
Requires-Dist: tqdm
Requires-Dist: orjson
Requires-Dist: selectolax
Requires-Dist: uvloop ; platform_system != "Windows"
